pyrtz/__init__.py
pyrtz/annocp.py
pyrtz/asylum.py
pyrtz/curves.py
pyrtz/utils.py
pyrtz-0.1.8.dist-info/LICENSE
pyrtz-0.1.8.dist-info/WHEEL
pyrtz-0.1.8.dist-info/METADATA
pyrtz-0.1.8.dist-info/RECORD
