Metadata-Version: 2.1
Name: pyrtz
Version: 0.1.8
Summary: Force spectroscopy in Python
Home-page: https://github.com/nstone8/pyrtz
Author: Nicholas Stone
Author-email: stone.nicholas@gmail.com
Requires-Python: >=3.8
Classifier: Development Status :: 4 - Beta
Classifier: Framework :: Dash
Classifier: Intended Audience :: Science/Research
Classifier: License :: OSI Approved :: GNU General Public License v3 (GPLv3)
Classifier: Operating System :: OS Independent
Classifier: Topic :: Scientific/Engineering
Requires-Dist: numpy >=1.18.5
Requires-Dist: pandas >=1.0.5
Requires-Dist: scipy >=1.4.1
Requires-Dist: plotly >=5.1.0
Requires-Dist: dash >=1.21.0
Requires-Dist: dash_core_components >=1.17.1
Requires-Dist: dash_html_components >=1.1.4
Requires-Dist: PyPDF2 >=1.26.0
Requires-Dist: igor2 >=0.5.5
Requires-Dist: kaleido >=0.2.1
